arizona_ai_sdk/__init__.py
arizona_ai_sdk/client.py
arizona_ai_sdk/exceptions.py
arizona_ai_sdk/http_client.py
arizona_ai_sdk/types.py
arizona_ai_sdk/utils.py
arizona_ai_sdk/api/__init__.py
arizona_ai_sdk/api/chat.py
arizona_ai_sdk/api/configs.py
arizona_ai_sdk/api/forum.py
arizona_ai_sdk/api/models.py
arizona_ai_sdk/api/tokens.py
arizona_ai_sdk/api/user.py
arizona_ai_sdk/models/__init__.py
arizona_ai_sdk/models/base.py
arizona_ai_sdk/models/chat.py
arizona_ai_sdk/models/config.py
arizona_ai_sdk/models/forum.py
arizona_ai_sdk/models/model.py
arizona_ai_sdk/models/tokens.py
arizona_ai_sdk/models/user.py
arizona_ai_sdk-1.0.0.dist-info/licenses/LICENSE
arizona_ai_sdk-1.0.0.dist-info/METADATA
arizona_ai_sdk-1.0.0.dist-info/WHEEL
arizona_ai_sdk-1.0.0.dist-info/top_level.txt
arizona_ai_sdk-1.0.0.dist-info/RECORD
