Metadata-Version: 2.4
Name: arizona_ai_sdk
Version: 1.0.0
Summary: Python SDK для ArizonaAI API
Home-page: https://github.com/Arizona-AI/arizona-ai-python-sdk
Author: ArizonaAI
Author-email: fakelag28 <fakelag712@gmail.com>
License: GPL-2.0
Project-URL: Homepage, https://arizona-ai.ru
Project-URL: Documentation, https://arizona-ai.ru/api-docs
Project-URL: Repository, https://github.com/Arizona-AI/arizona-ai-python-sdk
Keywords: arizona-ai-sdk,api,sdk,ai,chat,gpt
Classifier: Development Status :: 5 - Production/Stable
Classifier: Intended Audience :: Developers
Classifier: License :: OSI Approved :: GNU General Public License v2 (GPLv2)
Classifier: Operating System :: OS Independent
Classifier: Programming Language :: Python :: 3
Classifier: Programming Language :: Python :: 3.8
Classifier: Programming Language :: Python :: 3.9
Classifier: Programming Language :: Python :: 3.10
Classifier: Programming Language :: Python :: 3.11
Classifier: Programming Language :: Python :: 3.12
Classifier: Topic :: Software Development :: Libraries :: Python Modules
Classifier: Typing :: Typed
Requires-Python: >=3.8
License-File: LICENSE
Requires-Dist: httpx>=0.24.0
Provides-Extra: dev
Requires-Dist: pytest>=7.0.0; extra == "dev"
Requires-Dist: pytest-asyncio>=0.21.0; extra == "dev"
Requires-Dist: black>=23.0.0; extra == "dev"
Requires-Dist: mypy>=1.0.0; extra == "dev"
Dynamic: author
Dynamic: home-page
Dynamic: license-file
Dynamic: requires-python
